README.rst
setup.cfg
setup.py
browser/__init__.py
browser/plugin.py
browser/pytest_browser.py
pytest_browser.egg-info/PKG-INFO
pytest_browser.egg-info/SOURCES.txt
pytest_browser.egg-info/dependency_links.txt
pytest_browser.egg-info/entry_points.txt
pytest_browser.egg-info/not-zip-safe
pytest_browser.egg-info/requires.txt
pytest_browser.egg-info/top_level.txt