Metadata-Version: 1.1
Name: pytest-browser
Version: 0.2.0
Summary: A pytest plugin for console based browser test selection just after the collection phase
Home-page: https://github.com/mehmetg/pytest-browser
Author: Mehmet Gerceker
Author-email: mehmetg@msn.com
License: MIT
Download-URL: https://github.com/mehmetg/pytest-browser/archive/0.2.0.tar.gz
Keywords: py.test pytest plugin browse interactive
Platform: linux
Platform: macos
Classifier: Development Status :: 3 - Alpha
Classifier: Intended Audience :: Developers
Classifier: License :: OSI Approved :: MIT License
Classifier: Operating System :: POSIX
Classifier: Operating System :: Microsoft :: Windows
Classifier: Operating System :: MacOS :: MacOS X
Classifier: Topic :: Software Development :: Testing
Classifier: Programming Language :: Python
Classifier: Environment :: Console
